paradoxism/__init__.py
paradoxism/config.py
paradoxism/context.py
paradoxism/model_infos.json
paradoxism/model_infos_ui.py
paradoxism/oai_sample.json
paradoxism/assets/NotoSansTC-Thin.ttf
paradoxism/base/__init__.py
paradoxism/base/agent.py
paradoxism/base/flow.py
paradoxism/base/knowledge.py
paradoxism/base/loop.py
paradoxism/base/perfm.py
paradoxism/base/tool.py
paradoxism/llm/__init__.py
paradoxism/llm/base.py
paradoxism/llm/claude.py
paradoxism/llm/gemini.py
paradoxism/llm/ollama.py
paradoxism/llm/openai.py
paradoxism/ops/__init__.py
paradoxism/ops/ast.py
paradoxism/ops/base.py
paradoxism/ops/convert.py
paradoxism/tools/__init__.py
paradoxism/tools/image_tools.py
paradoxism/tools/ppt_tools.py
paradoxism/tools/stock_tools.py
paradoxism/tools/tool.py
paradoxism/tools/web_tools.py
paradoxism/utils/__init__.py
paradoxism/utils/docstring_utils.py
paradoxism/utils/image_utils.py
paradoxism/utils/input_dict_utils.py
paradoxism/utils/markdown_utils.py
paradoxism/utils/regex_utils.py
paradoxism/utils/text_utils.py
paradoxism/utils/web_utils.py
paradoxism/utils/web_utils_old.py
paradoxism-0.0.4.dist-info/LICENSE
paradoxism-0.0.4.dist-info/METADATA
paradoxism-0.0.4.dist-info/WHEEL
paradoxism-0.0.4.dist-info/entry_points.txt
paradoxism-0.0.4.dist-info/top_level.txt
paradoxism-0.0.4.dist-info/RECORD
