Metadata-Version: 2.1
Name: paradoxism
Version: 0.0.4
Summary: Prompt like a Human, Perform like a Machine
Download-URL: https://test.pypi.org/project/paradoxism
Author: Allan Yiin
Author-email: allanyiin.ai@gmail.com
License: MIT
Keywords: chatgpt,gpt4,llm,prompt
Classifier: Development Status :: 4 - Beta
Classifier: Intended Audience :: Developers
Classifier: Intended Audience :: Education
Classifier: Intended Audience :: Science/Research
Classifier: License :: OSI Approved :: MIT License
Classifier: Programming Language :: Python :: 3.10
Classifier: Programming Language :: Python :: 3.11
Classifier: Programming Language :: Python :: 3.12
Classifier: Topic :: Software Development :: Libraries
Classifier: Topic :: Software Development :: Libraries :: Python Modules
Requires-Python: >=3.10
License-File: LICENSE
Requires-Dist: fastapi
Requires-Dist: uvicorn
Requires-Dist: sqlalchemy
Requires-Dist: apscheduler
Provides-Extra: tests
Requires-Dist: pytest; extra == "tests"
Requires-Dist: pytest-pep8; extra == "tests"
Requires-Dist: pytest-xdist; extra == "tests"
Requires-Dist: pytest-cov; extra == "tests"
Requires-Dist: requests; extra == "tests"
Requires-Dist: markdown; extra == "tests"
